slonq/__init__.py
slonq/py.typed
slonq/slonq.abi3.so
slonq/slonq.pyi
slonq-0.0.0.dist-info/METADATA
slonq-0.0.0.dist-info/WHEEL
slonq-0.0.0.dist-info/licenses/LICENSE
slonq-0.0.0.dist-info/RECORD
