Metadata-Version: 2.4
Name: slonq
Version: 0.0.0
Classifier: Programming Language :: Rust
Classifier: Programming Language :: Python :: Implementation :: CPython
Classifier: Programming Language :: Python :: Implementation :: PyPy
Classifier: License :: OSI Approved :: MIT License
License-File: LICENSE
Summary: A reliable, lightweight PostgreSQL job queue. Uses FOR UPDATE SKIP LOCKED for atomic, concurrent task distribution without external dependencies.
Author-email: Borislav Borisov <chmodas@astutebits.com>
License-Expression: MIT
Requires-Python: >=3.11
Project-URL: Homepage, https://github.com/astutebits/slonq
Project-URL: Issues, https://github.com/astutebits/slonq/issues
Project-URL: Repository, https://github.com/astutebits/slonq
